{
  "id": "pull-secrets",
  "title": "Pull secrets",
  "description": "Learn how to configure access to older Official providers versions from the Marketplace",
  "source": "@site/docs/providers/pull-secrets.md",
  "sourceDirName": ".",
  "slug": "/pull-secrets",
  "permalink": "/providers/pull-secrets",
  "draft": false,
  "unlisted": false,
  "tags": [],
  "version": "current",
  "frontMatter": {
    "title": "Pull secrets",
    "weight": 8,
    "description": "Learn how to configure access to older Official providers versions from the Marketplace"
  },
  "sidebar": "providersSidebar",
  "previous": {
    "title": "Migrate from Terraform to Crossplane or Upbound",
    "permalink": "/providers/provider-terraform/migrate-provider-tf"
  },
  "next": {
    "title": "Signature Verification",
    "permalink": "/providers/signature-verification"
  }
}