{
  "id": "gitops",
  "title": "GitOps with control planes",
  "description": "An introduction to doing GitOps with control planes on Upbound",
  "source": "@site/docs/connect/gitops.md",
  "sourceDirName": ".",
  "slug": "/gitops",
  "permalink": "/connect/gitops",
  "draft": false,
  "unlisted": false,
  "tags": [],
  "version": "current",
  "frontMatter": {
    "title": "GitOps with control planes",
    "weight": 90,
    "description": "An introduction to doing GitOps with control planes on Upbound",
    "aliases": [
      "/mcp/gitops",
      "/spaces/control-plane-connector",
      "mcp/gitops"
    ]
  },
  "sidebar": "connectSidebar",
  "previous": {
    "title": "Git integration",
    "permalink": "/connect/git-integration"
  },
  "next": {
    "title": "Consume control plane APIs in an app cluster with control plane connector",
    "permalink": "/connect/mcp-connector-guide"
  }
}